anpylar/__init__.py
anpylar/__version__.py
anpylar/anpylar.py
anpylar/app_component.py
anpylar/app_module.py
anpylar/application.py
anpylar/application_styles.py
anpylar/bundle.py
anpylar/component.py
anpylar/logconfig.py
anpylar/minify.py
anpylar/module.py
anpylar/packaging.py
anpylar/paketize.py
anpylar/pip.py
anpylar/serve.py
anpylar/syntaxcheck.py
anpylar/utils.py
anpylar/version.py
anpylar/webpack.py
anpylar/data/LICENSE.brython
anpylar/data/__init__.py
anpylar/data/anpylar.auto_vfs.js
anpylar/data/anpylar_d.auto_vfs.js
anpylar/data/anpylar_js.js
anpylar/data/brython.js
anpylar/data/brython_stdlib.js
anpylar-1.1.5.dist-info/DESCRIPTION.rst
anpylar-1.1.5.dist-info/METADATA
anpylar-1.1.5.dist-info/RECORD
anpylar-1.1.5.dist-info/WHEEL
anpylar-1.1.5.dist-info/entry_points.txt
anpylar-1.1.5.dist-info/metadata.json
anpylar-1.1.5.dist-info/top_level.txt
