Metadata-Version: 2.0
Name: anpylar
Version: 1.1.5
Summary: Command Line Interface for AnPyLar
Home-page: https://github.com/anpylar/anpylar-cli
Author: The AnPyLar Team
Author-email: anpylar@anpylar.com
License: MIT
Download-URL: https://github.com/anpylar/anpylar-cli/tarball/1.1.5
Keywords: web,development
Platform: UNKNOWN
Classifier: Development Status :: 5 - Production/Stable
Classifier: Intended Audience :: Developers
Classifier: Topic :: Software Development
Classifier: License :: OSI Approved :: MIT License
Classifier: Programming Language :: Python :: 3
Classifier: Operating System :: OS Independent
